zqybxqqwetest/__init__.py
zqybxqqwetest/coordTransform.py
zqybxqqwetest/useragents.py
zqybxqqwetest/zqy.py
zqybxqqwetest-1.0.1.dist-info/DESCRIPTION.rst
zqybxqqwetest-1.0.1.dist-info/METADATA
zqybxqqwetest-1.0.1.dist-info/RECORD
zqybxqqwetest-1.0.1.dist-info/WHEEL
zqybxqqwetest-1.0.1.dist-info/metadata.json
zqybxqqwetest-1.0.1.dist-info/top_level.txt
zqybxqqwetest-1.0.1.dist-info/zip-safe
